cne/__init__.py
cne/_cne.py
cne/callbacks.py
cne/cne.py
cne/old_loss_implementation.py
contrastive_ne-0.4.0.dist-info/licenses/LICENSE
contrastive_ne-0.4.0.dist-info/METADATA
contrastive_ne-0.4.0.dist-info/WHEEL
contrastive_ne-0.4.0.dist-info/top_level.txt
contrastive_ne-0.4.0.dist-info/RECORD
