Metadata-Version: 2.4
Name: contrastive-ne
Version: 0.4.0
Summary: Contrastive Neighbor Embeddings
Author-email: Sebastian Damrich <sebastian.damrich@uni-tuebingen.de>, Niklas Böhm <jan-niklas.boehm@uni-tuebingen.de>
License: MIT
Project-URL: homepage, https://github.com/berenslab/contrastive-ne
Classifier: Programming Language :: Python :: 3
Requires-Python: >=3.8
License-File: LICENSE
Requires-Dist: numpy>=1.17
Requires-Dist: scikit-learn>=0.23.2
Requires-Dist: annoy
Requires-Dist: matplotlib
Requires-Dist: torchvision
Requires-Dist: torch>=1.10
Requires-Dist: scipy
Requires-Dist: pykeops
Dynamic: license-file
